index_analysis/__init__.py
index_analysis/cone/__init__.py
index_analysis/cone/keycc.py
index_analysis-1.0.0.dist-info/DESCRIPTION.rst
index_analysis-1.0.0.dist-info/METADATA
index_analysis-1.0.0.dist-info/RECORD
index_analysis-1.0.0.dist-info/WHEEL
index_analysis-1.0.0.dist-info/metadata.json
index_analysis-1.0.0.dist-info/top_level.txt
